{"attributes": {"imagesize": " 60px'''House Hornwood''' is a vassal house that holds fealty to House Stark of Winterfell. Their lands are southeast of Winterfell, located in a forested region. Their stronghold is a castle also called Hornwood. The Hornwood lands border the holdings of House Manderly to the south and House Bolton to the northeast.The Hornwood sigil is a brown bull moose on an orange field. Their motto is '''&quot;Righteous in Wrath.&quot;'''&lt;ref&gt;&quot;The Wolf and the Lion&quot;&lt;/ref&gt; They accompanied Robb Stark when he called his bannermen.&lt;ref&gt;&quot;The Pointy End&quot;&lt;/ref&gt;==Image Gallery==&lt;gallery&gt;House Hornwood tourney.jpg", "founder": "", "title": "House Hornwood", "image": "House Hornwood.png", "heir": "", "sigil": "A brown bull moose on an orange field.", "seat": "Hornwood", "religion": "Old Gods", "titles": "", "allegiance": "House Stark", "words": "&quot;Righteous in Wrath&quot;", "lord": "", "age": "", "region": "The North", "vassals": ""}, "sections": {"TOP": "House Hornwood031212rk1m81ljuoh09mbv68ip406v5shoqa1569352014-08-15T18:05:43ZThe Boy Who Cried Direwolf5928719{{Noble house\n| Title=[[House Hornwood]]\n| Image=House Hornwood.png\n| Sigil=A brown bull moose on an orange field.\n| Words=&quot;Righteous in Wrath&quot;\n| Titles=\n| Seat=[[Hornwood]]\n| Region=The [[North]]\n| Lord=\n| Heir=\n| Allegiance=[[House Stark]]\n| Religion=[[Old Gods]]\n| Vassals=\n| Age=\n| Founder=\n| ImageSize = 60px}}\n\n'''House Hornwood''' is a vassal house that holds fealty to [[House Stark]] of [[Winterfell]]. Their lands are southeast of Winterfell, located in a forested region. Their stronghold is a castle also called [[Hornwood]]. The Hornwood lands border the holdings of House Manderly to the south and [[House Bolton]] to the northeast.\n\nThe Hornwood sigil is a brown bull moose on an orange field. Their motto is '''&quot;Righteous in Wrath.&quot;'''&lt;ref&gt;&quot;[[The Wolf and the Lion]]&quot;&lt;/ref&gt; They accompanied [[Robb Stark]] when he called his bannermen.&lt;ref&gt;&quot;[[The Pointy End]]&quot;&lt;/ref&gt;\n\n", "Image Gallery": "&lt;gallery&gt;\nHouse Hornwood tourney.jpg|The banner of House Hornwood at the [[Tournament|Tourney of the Hand]] in &quot;[[The Wolf and the Lion]]&quot;.\nHouse Hornwood.png|HBO viewers guide icon for House Hornwood.\n&lt;/gallery&gt;\n\n", "See also": "* {{AWOIAF}} (MAJOR spoilers from the books)\n\n", "In the books": "In ''[[A Song of Ice and Fire]]\u00c2\u00a0''novels, House Hornwood is a loyal vassal of the Starks. House Bolton is said to have designs on their fertile lands.\n\nWhen [[Robb Stark]] summoned his bannermen, Lord Halys Hornwood and his son Daryn went to [[Winterfell]] and joined his army. Daryn became one of Robb's personal guards. Both of them were killed in the subsequent battles.\n\nOnce [[Ramsay Snow]] learned about the death of Halys and Daryn, he kidnapped Lady Donella, raped her, and forced her to marry him and to sign a will naming him the sole heir of the Hornwood lands. Then he locked her in a cell and did not bring her food. When Ser [[Rodrik Cassel]] arrived to save her, it was too late: she starved to death after chewing several of her fingers.\n\n'''Members'''\n* Lord {Halys Hornwood}, the head of the family. Slain at the [[Battle of the Green Fork]].\n* Lady {Donella Manderly}, Lord Halys's wife.\n** {Daryn Hornwood}, Lord Halys's son and heir. Slain by [[Jaime Lannister]] at the [[Battle of the Whispering Wood]].\n** Larence Snow, the Bastard of Hornwood, Lord Halys's illegitimate son. Fostered at [[Deepwood Motte]].\n* Lady Berena Hornwood, Lord Halys' sister, wed to Leobald Tallhart. Currently held captive by the [[ironborn]] at [[Torrhen's Square]].\n\n"}, "title": "House Hornwood"}