{"attributes": {"weapon": "Dawn", "imagesize": "150'''House Dayne''' is a noble house from Dorne. They are vassals to House Martell of Sunspear. Their seat is the castle of Starfall.Their ancestral weapon is Dawn, a blade forged from the metal of a fallen star. The Dayne knight that bears the sword is granted the title of &quot;the Sword of the Morning&quot;.\u00c2\u00a0==Known members==* Lord Beric Dayne, Lord of Starfall** Ser Arthur Dayne, the Sword of the Morning, his second son, killed during Robert's Rebellion.==In the books==In the ''A Song of Ice and Fire'' novels, members of House Dayne are Stony Dornishmen, whose characteristics mostly resemble the rest of the Seven Kingdoms in look, customs and traditions (being composed of the same First Men/Andals", "founder": "", "title": "House Dayne", "image": "DayneSigil.jpg", "heir": "", "sigil": "A sword and a falling star on a lavender background", "seat": "Starfall", "age": "", "titles": "Lord of Starfall", "allegiance": "House Martell", "words": "", "lord": "", "region": "Dorne", "vassals": ""}, "sections": {"TOP": "House Dayne022306ldo7mbesw15w10d4ww6d2gctorjork51587122014-09-08T23:26:04ZGonzalo848331/* In the books */{{Noble house\n| Title=House Dayne\n| Image=DayneSigil.jpg\n| Sigil=A sword and a falling star on a lavender background\n| Words=\n| Titles=Lord of Starfall\n| Seat=[[Starfall]]\n| Region=[[Dorne]]\n| Lord=\n| Heir=\n| Allegiance=[[House Martell]]\n| Vassals=\n| Age=\n| Founder=\n| Weapon=[[Dawn]]\n| ImageSize=150}}\n\n'''House Dayne''' is a [[noble house]] from [[Dorne]]. They are vassals to [[House Martell]] of [[Sunspear]]. Their seat is the castle of [[Starfall]].\n\nTheir ancestral weapon is [[Dawn]], a blade forged from the metal of a fallen star. The Dayne knight that bears the sword is granted the title of &quot;the [[Sword of the Morning]]&quot;.\u00c2\u00a0\n\n", "Known members": "* Lord {[[Beric Dayne]]}, Lord of Starfall\n** Ser {[[Arthur Dayne]]}, the Sword of the Morning, his second son, killed during [[Robert's Rebellion]].\n\n", "In the books": "In the ''[[A Song of Ice and Fire]]'' novels, members of House Dayne are Stony [[Dornishmen]], whose characteristics mostly resemble the rest of the [[Seven Kingdoms]] in look, customs and traditions (being composed of the same [[First Men]]/[[Andals|Andal]] mixture). Unlike the rest of the more [[Rhoynar|Rhoynish]]-looking Dornishmen, they have pale skin with hair ranging from dark brown to pale blond and they often have violet eyes, though according to [[George R.R. Martin]] they are not of [[Valyrian]] descent.\n\nMembers in the books:\n\n*Lord Edric &quot;Ned&quot; Dayne, Lord of [[Starfall]]. A member of the [[Brotherhood Without Banners]] and a squire of [[Beric Dondarrion]].\n**Ser {Arthur Dayne} aka the Sword of the Morning, his uncle. Died at the Tower of Joy.\n**{Ashara Dayne}, his aunt. The manner of her death remains a mystery.\n**Allyria Dayne, his aunt.\n**Gerold Dayne aka Darkstar, cousin of Arthur and Edric from an unknown distant relative.\n\n"}, "title": "House Dayne"}