{"attributes": {"founder": "'''House Selmy''' is a vassal house from the Stormlands that holds fealty to House Baratheon of Storm's End.== Known members ==* Ser Barristan Selmy, known as &quot;Barristan the Bold&quot;, former Lord Commander of the Kingsguard. \u00c2\u00a0Since being dismissed by King Joffrey Baratheon,\u00c2\u00a0he tracked down Daenerys Targaryen and swore his loyalty to her.==In the books==In the ''A Song of Ice and Fire'' novels, House Selmy is a house sworn to Storm's End. Their seat is Harvest Hall and their sigil is three stalks of yellow wheat on brown.==See also==* AWOIAF (spoilers from the books)Storm HousesCategory:Noble houses", "title": "House Selmy", "image": "", "heir": "", "sigil": "Three stalks of yellow wheat on brown", "seat": "Harvest Hall", "age": "", "titles": "", "allegiance": "House Baratheon", "words": "", "lord": "", "region": "The Stormlands", "vassals": ""}, "sections": {"TOP": "House Selmy031250tjzr3cgkbmumoctae9lpxcidwkluf31681502014-12-24T17:14:42ZSer Patrek25358400{{Noble house\n| Title=[[House Selmy]]\n| Image=\n| Sigil=Three stalks of yellow wheat on brown\n| Words=\n| Titles=\n| Seat=Harvest Hall\n| Region=The [[Stormlands]]\n| Lord=\n| Heir=\n| Allegiance=[[House Baratheon]]\n| Vassals=\n| Age=\n| Founder=}}\n'''House Selmy''' is a vassal house from the [[Stormlands]] that holds fealty to [[House Baratheon]] of [[Storm's End]].\n\n", "In the books": "In the ''[[A Song of Ice and Fire]]'' novels, House Selmy is a house sworn to Storm's End. Their seat is Harvest Hall and their sigil is three stalks of yellow wheat on brown.\n\n", " Known members ": "* Ser [[Barristan Selmy]], known as &quot;Barristan the Bold&quot;, former Lord Commander of the [[Kingsguard]]. \u00c2\u00a0Since being dismissed by King [[Joffrey Baratheon]],\u00c2\u00a0he tracked down [[Daenerys Targaryen]] and swore his loyalty to her.\n\n"}, "title": "House Selmy"}