{"attributes": {"cadets": "", "weapon": "'''House Velaryon''' is a vassal house that holds fealty to House Baratheon of Dragonstone. Their seat is Driftmark, an island in Blackwater Bay located west of Dragonstone.==Historical members==* Monica Velaryon, wife of the firstborn son and heir of Lord Orys Baratheon.&lt;ref&gt;&quot;A Golden Crown&quot;&lt;/ref&gt;==In the books==In the ''A Song of Ice and Fire'' novels, House Velaryon an ancient and proud house, with the blood of old Valyria in its veins and sometimes married into House Targaryen both before and after the War of Conquest. Velaryons, like the Targaryens are born with the Valyrian features of silver-blond hair and purple eyes. They rule over Driftmark, the largest island of the Blackwater Bay, and are sworn to Dragonstone. Their arms depict a silver seahorse on sea green and their titles are Lord of the Tides and Master of Driftmark. Their words do not appear in the books, but according to semi-canon sources they are &quot;The Old, the True, the Brave&quot;.===Members===* Lord Monford Velaryon, Lord of the Tides and Master of Driftmark.** Monterys Velaryon, his son and heir, a young boy.* Aurane Waters, known as the Bastard of Driftmark. Bastard half-brother of Lord Monford.==See also==* AWOIAF (spoilers from the books)==References==Reflist", "founder": "", "title": "House Velaryon", "image": "", "heir": "", "sigil": "A silver seahorse on sea green", "seat": "Driftmark", "age": "", "titles": "", "allegiance": "House Baratheon of Dragonstone", "words": "&quot;The Old, the True, the Brave&quot;", "lord": "", "region": "Blackwater Bay", "vassals": ""}, "sections": {"TOP": "House Velaryon012756mxcgj5xfar84hxombestmnkvp272mw31586932014-09-08T22:07:49ZGonzalo848331Adding categories{{Noble house\n| Title=[[House Velaryon]]\n| Image=\n| Sigil=A silver seahorse on sea green\n| Words=&quot;The Old, the True, the Brave&quot;\n| Titles=\n| Seat=[[Driftmark]]\n| Region=[[Blackwater Bay]]\n| Lord=\n| Heir=\n| Allegiance=[[House Baratheon of Dragonstone]]\n| Vassals=\n| Cadets=\n| Age=\n| Founder=\n| Weapon=}}\n'''House Velaryon''' is a vassal house that holds fealty to [[House Baratheon of Dragonstone]]. Their seat is [[Driftmark]], an island in [[Blackwater Bay]] located west of [[Dragonstone]].\n\n", "See also": "* {{AWOIAF}} (spoilers from the books)\n\n", "In the books": "\nIn the ''[[A Song of Ice and Fire]]'' novels, House Velaryon an ancient and proud house, with the blood of old [[Valyria]] in its veins and sometimes married into [[House Targaryen]] both before and after the [[War of Conquest]]. Velaryons, like the Targaryens are born with the Valyrian features of silver-blond hair and purple eyes. They rule over Driftmark, the largest island of the Blackwater Bay, and are sworn to Dragonstone. Their arms depict a silver seahorse on sea green and their titles are Lord of the Tides and Master of Driftmark. Their words do not appear in the books, but according to semi-canon sources they are &quot;The Old, the True, the Brave&quot;.\n\n===Members===\n\n* Lord Monford Velaryon, Lord of the Tides and Master of Driftmark.\n** Monterys Velaryon, his son and heir, a young boy.\n* Aurane Waters, known as the Bastard of Driftmark. Bastard half-brother of Lord Monford.\n\n", "Historical members": "\n* {[[Monica Velaryon]]}, wife of the firstborn son and heir of Lord [[Orys Baratheon]].&lt;ref&gt;&quot;[[A Golden Crown]]&quot;&lt;/ref&gt;\n\n"}, "title": "House Velaryon"}