{"attributes": {"status": " :Category:Status: Dead", "rightlink": " KingsguardCharacter", "season": "Season 4", "image": " Oswell Whent.png'''Oswell Whent''' is an unseen character in ''Game of Thrones''. He is not expected to appear in the series, being long dead by the time it starts. Ser Oswell Whent was a knight of House Whent a sworn brother of the Kingsguard of Aerys II Targaryen.==Biography=====Season 4===Ser Oswell is mentioned in the entry of his sworn brother, Lord Commander Gerold Hightower as recorded in ''The Book of Brothers''. The entry mentions the death of Ser Oswell along with Ser Gerold and Ser Arthur Dayne, fighting a small force led by Eddard Stark in the Red Mountains after refusing to bend the knee to the new king, Robert Baratheon.&lt;ref&gt;&quot;Two Swords&quot;&lt;/ref&gt;==In the books==In the ''A Song of Ice and Fire'' novels, Ser Oswell Whent was a younger brother of Lord Whent, known and remembered for his dark humor. He wore a distinctive helmet emblazoned with a black bat with its wings spread, symbolizing House Whent. Oswell was present at the Tourney at Harrenhal where Jaime Lannister became a Kingsguard.==See also==*AWOIAF (spoilers from the books)==References==ReflistMadKingKingsguardDEFAULTSORT:Whent, OswellCategory:CharactersCategory:Mentioned CharactersCategory:Status: DeadCategory:KingsguardCategory:KnightsCategory:House Whent", "leftimage": " Whent mini shield.png", "allegiance": ["Kingsguard", "House Whent"], "titles": "Ser", "rightimage": " Kingsguard mini shield.png", "place": "Harrenhal", "mentioned": "&quot;Two Swords&quot;", "title": "Oswell Whent", "first": "", "leftlink": " House Whent"}, "sections": {"TOP": "Oswell Whent02232150dbyelbb5is841t4wess3hidt2uw6x1749842015-03-02T17:14:47ZDaemon Targaryen24097499{{Heraldry|leftimage = Whent mini shield.png|leftlink = House Whent|rightimage = Kingsguard mini shield.png|rightlink = Kingsguard}}\n{{Character\n| Title=Oswell Whent\n| Season=[[Season 4|4]]\n| Mentioned=&quot;[[Two Swords]]&quot;\n|Titles=Ser\n| First=\n| Status= [[:Category:Status: Dead|Deceased]]\n| Place=[[Harrenhal]]\n| Allegiance=[[Kingsguard]]&lt;br&gt;[[House Whent]]\n|Image = Oswell Whent.png}}\n'''Oswell Whent''' is an unseen character in ''[[Game of Thrones]]''. He is not expected to appear in the series, being long dead by the time it starts. Ser Oswell Whent was a [[knight]] of [[House Whent]] a sworn brother of the [[Kingsguard]] of [[Aerys II Targaryen]].\n\n", "In the books": "In the ''[[A Song of Ice and Fire]]'' novels, Ser Oswell Whent was a younger brother of Lord Whent, known and remembered for his dark humor. He wore a distinctive helmet emblazoned with a black bat with its wings spread, symbolizing House Whent. Oswell was present at the [[Tourney]] at Harrenhal where [[Jaime Lannister]] became a Kingsguard.\n\n", "Biography": "===[[Season 4]]===\nSer Oswell is mentioned in the entry of his sworn brother, Lord Commander [[Gerold Hightower]] as recorded in ''[[The Book of Brothers]]''. The entry mentions the death of Ser Oswell along with Ser Gerold and Ser [[Arthur Dayne]], fighting a small force led by [[Eddard Stark]] in the [[Red Mountains]] after refusing to bend the knee to the new king, [[Robert Baratheon]].&lt;ref&gt;&quot;[[Two Swords]]&quot;&lt;/ref&gt;\n\n", "See also": "*{{AWOIAF}} (spoilers from the books)\n\n"}, "title": "Oswell Whent"}